pyinclude/__init__.py
pyinclude/date.py
pyinclude/explorer.py
pyinclude/math.py
pyinclude/savedata.py
pyinclude-0.60.3.dist-info/LICENSE.md
pyinclude-0.60.3.dist-info/METADATA
pyinclude-0.60.3.dist-info/WHEEL
pyinclude-0.60.3.dist-info/top_level.txt
pyinclude-0.60.3.dist-info/RECORD
