Metadata-Version: 2.1
Name: pyinclude
Version: 0.60.3
Summary: A collection of Python scripts to make it easyer, for Windows
Author-email: Harry Min Khant <harrymk64@gmail.com>
Maintainer-email: Harry Min Khant <harrymk64@gmail.com>
License: MIT License
Requires-Python: >=3.8
License-File: LICENSE.md
Requires-Dist: inflect
Requires-Dist: wxpython
